ipytorch/__init__.py
ipytorch/cluster.py
ipytorch/collect_env.py
ipytorch/ippmagic.py
ipytorch/logger.py
ipytorch/magic.py
ipytorch/utils/__init__.py
ipytorch/utils/ddp.py
ipytorch/utils/detect.py
ipytorch-0.1.0.dist-info/METADATA
ipytorch-0.1.0.dist-info/WHEEL
ipytorch-0.1.0.dist-info/RECORD
